Workbook
Name HoldRate_h: Assumptions!$B$6
Name K_factor: Assumptions!$B$14
Name LeadTime_L: Assumptions!$B$4
Name LossFn_Lz: Assumptions!$B$13
Name Margin_m: Assumptions!$B$7
Name OrderCost_K: Assumptions!$B$8
Name ReviewPeriod_R: Assumptions!$B$5
Name ServiceLevel: Assumptions!$B$10
Name ServiceZ: Assumptions!$B$11
Name UnitCost_c: Assumptions!$B$12
Name UnitPrice_p: Assumptions!$B$9

Sheet README
A1: Cost of forecast error: assumptions and sensitivity
A2: Data-derived inputs come from the Rossmann Store Sales pipeline (Kaggle, not redistributed).
A4: What is real and what is assumed
A5: Rossmann has NO stock, orders, lead times, costs or unit prices. Every yellow cell on the Assumptions sheet is an ASSUMPTION with a low/high range. The grey cells on Data_inputs are forecast-error sizes measured on the validation months (2015-01-01 to 2015-06-24).
A6: Sales is daily turnover, not units. One 'unit' here is EUR 1 of turnover (unit price p = 1 is a normalisation, not an estimate). The currency itself is the community reading, not an official statement.
A8: The one quantified finding
A9: Extra expected cost per store-year when the daily forecast error behaves like a promotion day instead of an ordinary day, under an order-up-to policy with safety stock sized from the forecast error. Descriptive and assumption-driven: it is not a measured saving.
A10: Sheets: Assumptions (inputs) > Data_inputs (measured errors) > Finding (formulas, CI) > Tornado > TwoWay > Checks.
A11: Errors are assumed uncorrelated across days when scaled by sqrt(R+L); the calibration table reports Ljung-Box so the optimism can be judged.

Sheet Assumptions
A1: Assumptions (yellow = ASSUMPTION, change me)
A3: Parameter | B3: Value | C3: Unit | D3: Low | E3: High | F3: Label | G3: Why this value
A4: Lead time L | B4: 5 | C4: days | D4: 2 | E4: 10 | F4: ASSUMPTION | G4: Typical depot-to-store lead time; Rossmann provides none
A5: Review period R | B5: 7 | C5: days | D5: 1 | E5: 14 | F5: ASSUMPTION | G5: Weekly store ordering cycle
A6: Holding cost rate h | B6: 0.25 | C6: per year | D6: 0.15 | E6: 0.35 | F6: ASSUMPTION | G6: Textbook retail carrying-cost range 20 to 30 percent
A7: Gross margin m (lost-sale cost) | B7: 0.3 | C7: share of price | D7: 0.15 | E7: 0.5 | F7: ASSUMPTION | G7: Foregone margin proxy for one lost sale; no margin data exists
A8: Order cost K | B8: 50 | C8: EUR per order | D8: 10 | E8: 150 | F8: ASSUMPTION | G8: Not part of the finding; shown for completeness
A9: Unit price p | B9: 1 | C9: EUR per unit | F9: ASSUMPTION | G9: Normalisation: 1 unit = EUR 1 of turnover
A10: Cycle service level | B10: 0.95 | C10: share | F10: ASSUMPTION | G10: Policy choice, not a cost
A11: z = NORMSINV(service level) | B11: =NORMSINV(ServiceLevel) -> 1.6448536 | F11: DERIVED (formula)
A12: Unit cost c = p (1 - m) | B12: =UnitPrice_p*(1-Margin_m) -> 0.7 | F12: DERIVED (formula)
A13: Loss function Lz = phi(z) - z (1 - Phi(z)) | B13: =NORMDIST(ServiceZ,0,1,FALSE)-ServiceZ*(1-NORMSDIST(ServiceZ)) -> 0.020892959 | F13: DERIVED (formula)
A14: k = extra EUR per year per EUR 1 of daily RMSE | B14: =SQRT(ReviewPeriod_R+LeadTime_L)*(ServiceZ*UnitPrice_p*(1-Margin_m)*HoldRate_h+(365/ReviewPeriod_R)*(NORMDIST(ServiceZ,0,1,FALSE)-ServiceZ*(1-NORMSDIST(ServiceZ)))*Margin_m*UnitPrice_p) -> 2.1292965 | F14: DERIVED (formula)

Sheet Data_inputs
A1: DATA-DERIVED: RMSE of the daily forecast error per store, validation months, horizons 1-14
A3: store | B3: ML rmse promo | C3: ML rmse non-promo | D3: n promo days | E3: n non-promo days | F3: mean daily sales | G3: seasonal-naive rmse promo | H3: seasonal-naive rmse non-promo
A4: 1 | B4: 846.03 | C4: 433.89392 | D4: 129 | E4: 146 | F4: 4539.7782 | G4: 1498.7761 | H4: 1135.6288
A5: 2 | B5: 746.59511 | C5: 456.92929 | D5: 131 | E5: 146 | F5: 4986.4549 | G5: 1861.0798 | H5: 1584.9603
A6: 3 | B6: 938.50597 | C6: 628.61259 | D6: 129 | E6: 146 | F6: 6878.8691 | G6: 2462.4621 | H6: 2165.4507
A7: 4 | B7: 1360.8126 | C7: 833.67737 | D7: 131 | E7: 146 | F7: 9778.8051 | G7: 3054.3269 | H7: 2337.2739
A8: 5 | B8: 632.36556 | C8: 391.41132 | D8: 131 | E8: 146 | F8: 4647.6173 | G8: 1718.5657 | H8: 1489.2747
A9: 6 | B9: 767.56828 | C9: 372.94467 | D9: 131 | E9: 146 | F9: 4811.639 | G9: 1583.012 | H9: 1356.0172
A10: 7 | B10: 1258.6518 | C10: 978.63865 | D10: 131 | E10: 146 | F10: 8692.5054 | G10: 2724.5525 | H10: 2584.9408
A11: 8 | B11: 832.49485 | C11: 554.67748 | D11: 131 | E11: 146 | F11: 6270.5415 | G11: 1949.1039 | H11: 1710.8929
A12: 9 | B12: 848.4901 | C12: 622.13577 | D12: 129 | E12: 146 | F12: 7568.5127 | G12: 2040.8419 | H12: 1876.7942
A13: 10 | B13: 730.74586 | C13: 566.44175 | D13: 131 | E13: 146 | F13: 5784.2419 | G13: 1232.747 | H13: 1126.8241
A14: 11 | B14: 1565.6465 | C14: 924.00456 | D14: 131 | E14: 146 | F14: 7516.7437 | G14: 2658.5662 | H14: 2063.3594
A15: 12 | B15: 1102.5677 | C15: 812.37037 | D15: 131 | E15: 146 | F15: 7861.3285 | G15: 2850.2636 | H15: 2587.6763
... A1118: 1115 | B1118: 1124.5438 | C1118: 739.17875 | D1118: 129 | E1118: 146 | F1118: 7108.2218 | G1118: 2432.8308 | H1118: 2173.5537

Sheet Finding
A1: Finding: extra cost per store-year, promo-like error minus ordinary-day error (EUR)
A3: store | B3: delta rmse (ML) | C3: Extra cost promo (ML) | D3: Extra cost non-promo (ML) | E3: Finding (ML) | F3: delta rmse (seasonal naive) | G3: Finding (seasonal naive)
A4: =Data_inputs!A4 -> 1 | B4: =Data_inputs!B4-Data_inputs!C4 -> 412.13607 | C4: =Data_inputs!B4*K_factor -> 1801.4487 | D4: =Data_inputs!C4*K_factor -> 923.88882 | E4: =C4-D4 -> 877.5599 | F4: =Data_inputs!G4-Data_inputs!H4 -> 363.14733 | G4: =F4*K_factor -> 773.24835 | J4: Mean finding, ML forecast (EUR per store-year) | K4: =AVERAGE(E4:E1118) -> 977.11743
A5: =Data_inputs!A5 -> 2 | B5: =Data_inputs!B5-Data_inputs!C5 -> 289.66581 | C5: =Data_inputs!B5*K_factor -> 1589.7224 | D5: =Data_inputs!C5*K_factor -> 972.93795 | E5: =C5-D5 -> 616.78441 | F5: =Data_inputs!G5-Data_inputs!H5 -> 276.11951 | G5: =F5*K_factor -> 587.94032 | J5: SD across stores | K5: =STDEV(E4:E1118) -> 702.70208
A6: =Data_inputs!A6 -> 3 | B6: =Data_inputs!B6-Data_inputs!C6 -> 309.89338 | C6: =Data_inputs!B6*K_factor -> 1998.3575 | D6: =Data_inputs!C6*K_factor -> 1338.5026 | E6: =C6-D6 -> 659.85489 | F6: =Data_inputs!G6-Data_inputs!H6 -> 297.01144 | G6: =F6*K_factor -> 632.42542 | J6: Stores (n) | K6: =COUNT(E4:E1118) -> 1115
A7: =Data_inputs!A7 -> 4 | B7: =Data_inputs!B7-Data_inputs!C7 -> 527.13521 | C7: =Data_inputs!B7*K_factor -> 2897.5735 | D7: =Data_inputs!C7*K_factor -> 1775.1463 | E7: =C7-D7 -> 1122.4272 | F7: =Data_inputs!G7-Data_inputs!H7 -> 717.053 | G7: =F7*K_factor -> 1526.8185 | J7: 95% CI low (t, across stores) | K7: =K4-TINV(0.05,K6-1)*K5/SQRT(K6) -> 935.82656
A8: =Data_inputs!A8 -> 5 | B8: =Data_inputs!B8-Data_inputs!C8 -> 240.95424 | C8: =Data_inputs!B8*K_factor -> 1346.4938 | D8: =Data_inputs!C8*K_factor -> 833.43076 | E8: =C8-D8 -> 513.06302 | F8: =Data_inputs!G8-Data_inputs!H8 -> 229.29092 | G8: =F8*K_factor -> 488.22837 | J8: 95% CI high (t, across stores) | K8: =K4+TINV(0.05,K6-1)*K5/SQRT(K6) -> 1018.4083
A9: =Data_inputs!A9 -> 6 | B9: =Data_inputs!B9-Data_inputs!C9 -> 394.62361 | C9: =Data_inputs!B9*K_factor -> 1634.3805 | D9: =Data_inputs!C9*K_factor -> 794.10978 | E9: =C9-D9 -> 840.27067 | F9: =Data_inputs!G9-Data_inputs!H9 -> 226.99471 | G9: =F9*K_factor -> 483.33905 | J9: 95% CI low (Python store bootstrap, static) | K9: 934.39035
A10: =Data_inputs!A10 -> 7 | B10: =Data_inputs!B10-Data_inputs!C10 -> 280.01319 | C10: =Data_inputs!B10*K_factor -> 2680.043 | D10: =Data_inputs!C10*K_factor -> 2083.8119 | E10: =C10-D10 -> 596.23111 | F10: =Data_inputs!G10-Data_inputs!H10 -> 139.61165 | G10: =F10*K_factor -> 297.27459 | J10: 95% CI high (Python store bootstrap, static) | K10: 1017.7383
A11: =Data_inputs!A11 -> 8 | B11: =Data_inputs!B11-Data_inputs!C11 -> 277.81737 | C11: =Data_inputs!B11*K_factor -> 1772.6284 | D11: =Data_inputs!C11*K_factor -> 1181.0728 | E11: =C11-D11 -> 591.55556 | F11: =Data_inputs!G11-Data_inputs!H11 -> 238.21106 | G11: =F11*K_factor -> 507.22198 | J11: Mean finding, seasonal-naive forecast | K11: =AVERAGE(G4:G1118) -> 603.63856
A12: =Data_inputs!A12 -> 9 | B12: =Data_inputs!B12-Data_inputs!C12 -> 226.35433 | C12: =Data_inputs!B12*K_factor -> 1806.687 | D12: =Data_inputs!C12*K_factor -> 1324.7115 | E12: =C12-D12 -> 481.97548 | F12: =Data_inputs!G12-Data_inputs!H12 -> 164.04767 | G12: =F12*K_factor -> 349.30613 | J12: Mean delta rmse (ML), EUR per day | K12: =AVERAGE(B4:B1118) -> 458.89214
A13: =Data_inputs!A13 -> 10 | B13: =Data_inputs!B13-Data_inputs!C13 -> 164.30411 | C13: =Data_inputs!B13*K_factor -> 1555.9746 | D13: =Data_inputs!C13*K_factor -> 1206.1225 | E13: =C13-D13 -> 349.85217 | F13: =Data_inputs!G13-Data_inputs!H13 -> 105.92299 | G13: =F13*K_factor -> 225.54145
A14: =Data_inputs!A14 -> 11 | B14: =Data_inputs!B14-Data_inputs!C14 -> 641.64189 | C14: =Data_inputs!B14*K_factor -> 3333.7255 | D14: =Data_inputs!C14*K_factor -> 1967.4797 | E14: =C14-D14 -> 1366.2458 | F14: =Data_inputs!G14-Data_inputs!H14 -> 595.20679 | G14: =F14*K_factor -> 1267.3718 | J14: Literal formula chain on the average store (ML), one line per step
A15: =Data_inputs!A15 -> 12 | B15: =Data_inputs!B15-Data_inputs!C15 -> 290.19735 | C15: =Data_inputs!B15*K_factor -> 2347.6936 | D15: =Data_inputs!C15*K_factor -> 1729.7774 | E15: =C15-D15 -> 617.91622 | F15: =Data_inputs!G15-Data_inputs!H15 -> 262.58732 | G15: =F15*K_factor -> 559.12627 | J15: sigma promo = mean rmse promo | K15: =AVERAGE(Data_inputs!B4:B1118) -> 1204.3605
A16: =Data_inputs!A16 -> 13 | B16: =Data_inputs!B16-Data_inputs!C16 -> 1123.5889 | C16: =Data_inputs!B16*K_factor -> 4431.4565 | D16: =Data_inputs!C16*K_factor -> 2039.0026 | E16: =C16-D16 -> 2392.4539 | F16: =Data_inputs!G16-Data_inputs!H16 -> -41.943748 | G16: =F16*K_factor -> -89.310677 | J16: sigma non-promo = mean rmse non-promo | K16: =AVERAGE(Data_inputs!C4:C1118) -> 745.46839
A17: =Data_inputs!A17 -> 14 | B17: =Data_inputs!B17-Data_inputs!C17 -> 263.50857 | C17: =Data_inputs!B17*K_factor -> 1620.2059 | D17: =Data_inputs!C17*K_factor -> 1059.1181 | E17: =C17-D17 -> 561.08789 | F17: =Data_inputs!G17-Data_inputs!H17 -> 207.62227 | G17: =F17*K_factor -> 442.08938 | J17: SS promo = z sigma sqrt(R+L) | K17: =ServiceZ*K15*SQRT(ReviewPeriod_R+LeadTime_L) -> 6862.3741
A18: =Data_inputs!A18 -> 15 | B18: =Data_inputs!B18-Data_inputs!C18 -> 456.56028 | C18: =Data_inputs!B18*K_factor -> 2363.3386 | D18: =Data_inputs!C18*K_factor -> 1391.1864 | E18: =C18-D18 -> 972.1522 | F18: =Data_inputs!G18-Data_inputs!H18 -> 333.00699 | G18: =F18*K_factor -> 709.07062 | J18: Holding promo = SS c h | K18: =K17*UnitCost_c*HoldRate_h -> 1200.9155
A19: =Data_inputs!A19 -> 16 | B19: =Data_inputs!B19-Data_inputs!C19 -> 239.79491 | C19: =Data_inputs!B19*K_factor -> 2038.3357 | D19: =Data_inputs!C19*K_factor -> 1527.7413 | E19: =C19-D19 -> 510.59446 | F19: =Data_inputs!G19-Data_inputs!H19 -> 351.50793 | G19: =F19*K_factor -> 748.46461 | J19: Shortage per cycle promo = sigma sqrt(R+L) Lz | K19: =K15*SQRT(ReviewPeriod_R+LeadTime_L)*LossFn_Lz -> 87.165994
A20: =Data_inputs!A20 -> 17 | B20: =Data_inputs!B20-Data_inputs!C20 -> 235.95091 | C20: =Data_inputs!B20*K_factor -> 1662.8761 | D20: =Data_inputs!C20*K_factor -> 1160.4667 | E20: =C20-D20 -> 502.40945 | F20: =Data_inputs!G20-Data_inputs!H20 -> 240.41744 | G20: =F20*K_factor -> 511.92001 | J20: Shortage cost promo = (365/R) * that * m p | K20: =(365/ReviewPeriod_R)*K19*Margin_m*UnitPrice_p -> 1363.5252
A21: =Data_inputs!A21 -> 18 | B21: =Data_inputs!B21-Data_inputs!C21 -> 300.20998 | C21: =Data_inputs!B21*K_factor -> 2005.7219 | D21: =Data_inputs!C21*K_factor -> 1366.4858 | E21: =C21-D21 -> 639.23607 | F21: =Data_inputs!G21-Data_inputs!H21 -> 190.19162 | G21: =F21*K_factor -> 404.97436 | J21: Extra promo = Holding + Shortage | K21: =K18+K20 -> 2564.4407
A22: =Data_inputs!A22 -> 19 | B22: =Data_inputs!B22-Data_inputs!C22 -> 291.64527 | C22: =Data_inputs!B22*K_factor -> 2133.4833 | D22: =Data_inputs!C22*K_factor -> 1512.484 | E22: =C22-D22 -> 620.99927 | F22: =Data_inputs!G22-Data_inputs!H22 -> 353.02121 | G22: =F22*K_factor -> 751.68683 | J22: SS non-promo | K22: =ServiceZ*K16*SQRT(ReviewPeriod_R+LeadTime_L) -> 4247.6342
A23: =Data_inputs!A23 -> 20 | B23: =Data_inputs!B23-Data_inputs!C23 -> 129.29631 | C23: =Data_inputs!B23*K_factor -> 3681.8092 | D23: =Data_inputs!C23*K_factor -> 3406.499 | E23: =C23-D23 -> 275.31019 | F23: =Data_inputs!G23-Data_inputs!H23 -> 47.606992 | G23: =F23*K_factor -> 101.3694 | J23: Holding non-promo | K23: =K22*UnitCost_c*HoldRate_h -> 743.33599
A24: =Data_inputs!A24 -> 21 | B24: =Data_inputs!B24-Data_inputs!C24 -> 234.45549 | C24: =Data_inputs!B24*K_factor -> 2047.5152 | D24: =Data_inputs!C24*K_factor -> 1548.2899 | E24: =C24-D24 -> 499.22526 | F24: =Data_inputs!G24-Data_inputs!H24 -> 277.48046 | G24: =F24*K_factor -> 590.83819 | J24: Shortage per cycle non-promo | K24: =K16*SQRT(ReviewPeriod_R+LeadTime_L)*LossFn_Lz -> 53.953523
A25: =Data_inputs!A25 -> 22 | B25: =Data_inputs!B25-Data_inputs!C25 -> 1172.1143 | C25: =Data_inputs!B25*K_factor -> 4494.967 | D25: =Data_inputs!C25*K_factor -> 1999.1882 | E25: =C25-D25 -> 2495.7789 | F25: =Data_inputs!G25-Data_inputs!H25 -> -77.555993 | G25: =F25*K_factor -> -165.13971 | J25: Shortage cost non-promo | K25: =(365/ReviewPeriod_R)*K24*Margin_m*UnitPrice_p -> 843.98725
A26: =Data_inputs!A26 -> 23 | B26: =Data_inputs!B26-Data_inputs!C26 -> 463.58009 | C26: =Data_inputs!B26*K_factor -> 2008.2385 | D26: =Data_inputs!C26*K_factor -> 1021.139 | E26: =C26-D26 -> 987.09946 | F26: =Data_inputs!G26-Data_inputs!H26 -> 289.87304 | G26: =F26*K_factor -> 617.22565 | J26: Extra non-promo | K26: =K23+K25 -> 1587.3232
A27: =Data_inputs!A27 -> 24 | B27: =Data_inputs!B27-Data_inputs!C27 -> 514.01157 | C27: =Data_inputs!B27*K_factor -> 2827.9201 | D27: =Data_inputs!C27*K_factor -> 1733.437 | E27: =C27-D27 -> 1094.483 | F27: =Data_inputs!G27-Data_inputs!H27 -> 504.19536 | G27: =F27*K_factor -> 1073.5814 | J27: FINDING = Extra promo - Extra non-promo (EUR per store-year) | K27: =K21-K26 -> 977.11743
A28: =Data_inputs!A28 -> 25 | B28: =Data_inputs!B28-Data_inputs!C28 -> 234.07252 | C28: =Data_inputs!B28*K_factor -> 3361.3949 | D28: =Data_inputs!C28*K_factor -> 2862.9851 | E28: =C28-D28 -> 498.40979 | F28: =Data_inputs!G28-Data_inputs!H28 -> 499.12458 | G28: =F28*K_factor -> 1062.7842
A29: =Data_inputs!A29 -> 26 | B29: =Data_inputs!B29-Data_inputs!C29 -> 399.80312 | C29: =Data_inputs!B29*K_factor -> 2168.0487 | D29: =Data_inputs!C29*K_factor -> 1316.7493 | E29: =C29-D29 -> 851.29938 | F29: =Data_inputs!G29-Data_inputs!H29 -> 265.9586 | G29: =F29*K_factor -> 566.30471
A30: =Data_inputs!A30 -> 27 | B30: =Data_inputs!B30-Data_inputs!C30 -> 405.97831 | C30: =Data_inputs!B30*K_factor -> 2514.3637 | D30: =Data_inputs!C30*K_factor -> 1649.9155 | E30: =C30-D30 -> 864.44821 | F30: =Data_inputs!G30-Data_inputs!H30 -> 479.8683 | G30: =F30*K_factor -> 1021.7819
A31: =Data_inputs!A31 -> 28 | B31: =Data_inputs!B31-Data_inputs!C31 -> 108.1724 | C31: =Data_inputs!B31*K_factor -> 1328.9094 | D31: =Data_inputs!C31*K_factor -> 1098.5783 | E31: =C31-D31 -> 230.33112 | F31: =Data_inputs!G31-Data_inputs!H31 -> 281.48469 | G31: =F31*K_factor -> 599.36437
A32: =Data_inputs!A32 -> 29 | B32: =Data_inputs!B32-Data_inputs!C32 -> 430.30144 | C32: =Data_inputs!B32*K_factor -> 2430.5828 | D32: =Data_inputs!C32*K_factor -> 1514.3435 | E32: =C32-D32 -> 916.23936 | F32: =Data_inputs!G32-Data_inputs!H32 -> 323.29233 | G32: =F32*K_factor -> 688.38524
A33: =Data_inputs!A33 -> 30 | B33: =Data_inputs!B33-Data_inputs!C33 -> 279.45435 | C33: =Data_inputs!B33*K_factor -> 1731.4999 | D33: =Data_inputs!C33*K_factor -> 1136.4587 | E33: =C33-D33 -> 595.04117 | F33: =Data_inputs!G33-Data_inputs!H33 -> 188.25606 | G33: =F33*K_factor -> 400.85297
A34: =Data_inputs!A34 -> 31 | B34: =Data_inputs!B34-Data_inputs!C34 -> 382.54589 | C34: =Data_inputs!B34*K_factor -> 2126.1942 | D34: =Data_inputs!C34*K_factor -> 1311.6406 | E34: =C34-D34 -> 814.55363 | F34: =Data_inputs!G34-Data_inputs!H34 -> 297.38713 | G34: =F34*K_factor -> 633.22538
A35: =Data_inputs!A35 -> 32 | B35: =Data_inputs!B35-Data_inputs!C35 -> 1246.1549 | C35: =Data_inputs!B35*K_factor -> 4823.2439 | D35: =Data_inputs!C35*K_factor -> 2169.8107 | E35: =C35-D35 -> 2653.4332 | F35: =Data_inputs!G35-Data_inputs!H35 -> 9.7939525 | G35: =F35*K_factor -> 20.854229
A36: =Data_inputs!A36 -> 33 | B36: =Data_inputs!B36-Data_inputs!C36 -> 332.17549 | C36: =Data_inputs!B36*K_factor -> 2256.5199 | D36: =Data_inputs!C36*K_factor -> 1549.2198 | E36: =C36-D36 -> 707.3001 | F36: =Data_inputs!G36-Data_inputs!H36 -> 242.44553 | G36: =F36*K_factor -> 516.23842
A37: =Data_inputs!A37 -> 34 | B37: =Data_inputs!B37-Data_inputs!C37 -> 305.10803 | C37: =Data_inputs!B37*K_factor -> 1933.092 | D37: =Data_inputs!C37*K_factor -> 1283.4265 | E37: =C37-D37 -> 649.66547 | F37: =Data_inputs!G37-Data_inputs!H37 -> 383.38 | G37: =F37*K_factor -> 816.3297
A38: =Data_inputs!A38 -> 35 | B38: =Data_inputs!B38-Data_inputs!C38 -> 711.13843 | C38: =Data_inputs!B38*K_factor -> 3280.0284 | D38: =Data_inputs!C38*K_factor -> 1765.8038 | E38: =C38-D38 -> 1514.2246 | F38: =Data_inputs!G38-Data_inputs!H38 -> 623.35146 | G38: =F38*K_factor -> 1327.3001
A39: =Data_inputs!A39 -> 36 | B39: =Data_inputs!B39-Data_inputs!C39 -> 630.85005 | C39: =Data_inputs!B39*K_factor -> 3580.9067 | D39: =Data_inputs!C39*K_factor -> 2237.6399 | E39: =C39-D39 -> 1343.2668 | F39: =Data_inputs!G39-Data_inputs!H39 -> 166.89683 | G39: =F39*K_factor -> 355.37283
... A1118: =Data_inputs!A1118 -> 1115 | B1118: =Data_inputs!B1118-Data_inputs!C1118 -> 385.36503 | C1118: =Data_inputs!B1118*K_factor -> 2394.4872 | D1118: =Data_inputs!C1118*K_factor -> 1573.9307 | E1118: =C1118-D1118 -> 820.55641 | F1118: =Data_inputs!G1118-Data_inputs!H1118 -> 259.27711 | G1118: =F1118*K_factor -> 552.07784

Sheet Tornado
A1: One-way sensitivity of the finding (EUR per store-year); order cost K does not enter the finding by construction
A3: Parameter | B3: Low | C3: High | D3: Finding at low | E3: Finding at high | F3: Swing | G3: Rank
A4: Lead time L (days) | B4: 2 | C4: 10 | D4: =Finding!$K$12*SQRT(ReviewPeriod_R+B4)*(ServiceZ*UnitPrice_p*(1-Margin_m)*HoldRate_h+(365/ReviewPeriod_R)*(NORMDIST(ServiceZ,0,1,FALSE)-ServiceZ*(1-NORMSDIST(ServiceZ)))*Margin_m*UnitPrice_p) -> 846.20851 | E4: =Finding!$K$12*SQRT(ReviewPeriod_R+C4)*(ServiceZ*UnitPrice_p*(1-Margin_m)*HoldRate_h+(365/ReviewPeriod_R)*(NORMDIST(ServiceZ,0,1,FALSE)-ServiceZ*(1-NORMSDIST(ServiceZ)))*Margin_m*UnitPrice_p) -> 1163.0024 | F4: =ABS(E4-D4) -> 316.79385 | G4: =RANK(F4,$F$4:$F$8) -> 4
A5: Review period R (days) | B5: 1 | C5: 14 | D5: =Finding!$K$12*SQRT(B5+LeadTime_L)*(ServiceZ*UnitPrice_p*(1-Margin_m)*HoldRate_h+(365/B5)*(NORMDIST(ServiceZ,0,1,FALSE)-ServiceZ*(1-NORMSDIST(ServiceZ)))*Margin_m*UnitPrice_p) -> 2895.1392 | E5: =Finding!$K$12*SQRT(C5+LeadTime_L)*(ServiceZ*UnitPrice_p*(1-Margin_m)*HoldRate_h+(365/C5)*(NORMDIST(ServiceZ,0,1,FALSE)-ServiceZ*(1-NORMSDIST(ServiceZ)))*Margin_m*UnitPrice_p) -> 902.64368 | F5: =ABS(E5-D5) -> 1992.4955 | G5: =RANK(F5,$F$4:$F$8) -> 1
A6: Holding rate h | B6: 0.15 | C6: 0.35 | D6: =Finding!$K$12*SQRT(ReviewPeriod_R+LeadTime_L)*(ServiceZ*UnitPrice_p*(1-Margin_m)*B6+(365/ReviewPeriod_R)*(NORMDIST(ServiceZ,0,1,FALSE)-ServiceZ*(1-NORMSDIST(ServiceZ)))*Margin_m*UnitPrice_p) -> 794.08563 | E6: =Finding!$K$12*SQRT(ReviewPeriod_R+LeadTime_L)*(ServiceZ*UnitPrice_p*(1-Margin_m)*C6+(365/ReviewPeriod_R)*(NORMDIST(ServiceZ,0,1,FALSE)-ServiceZ*(1-NORMSDIST(ServiceZ)))*Margin_m*UnitPrice_p) -> 1160.1492 | F6: =ABS(E6-D6) -> 366.06359 | G6: =RANK(F6,$F$4:$F$8) -> 3
A7: Margin m | B7: 0.15 | C7: 0.5 | D7: =Finding!$K$12*SQRT(ReviewPeriod_R+LeadTime_L)*(ServiceZ*UnitPrice_p*(1-B7)*HoldRate_h+(365/ReviewPeriod_R)*(NORMDIST(ServiceZ,0,1,FALSE)-ServiceZ*(1-NORMSDIST(ServiceZ)))*B7*UnitPrice_p) -> 815.4012 | E7: =Finding!$K$12*SQRT(ReviewPeriod_R+LeadTime_L)*(ServiceZ*UnitPrice_p*(1-C7)*HoldRate_h+(365/ReviewPeriod_R)*(NORMDIST(ServiceZ,0,1,FALSE)-ServiceZ*(1-NORMSDIST(ServiceZ)))*C7*UnitPrice_p) -> 1192.7391 | F7: =ABS(E7-D7) -> 377.33786 | G7: =RANK(F7,$F$4:$F$8) -> 2
A8: Order cost K (EUR) | B8: 10 | C8: 150 | D8: =Finding!$K$12*SQRT(ReviewPeriod_R+LeadTime_L)*(ServiceZ*UnitPrice_p*(1-Margin_m)*HoldRate_h+(365/ReviewPeriod_R)*(NORMDIST(ServiceZ,0,1,FALSE)-ServiceZ*(1-NORMSDIST(ServiceZ)))*Margin_m*UnitPrice_p) -> 977.11743 | E8: =Finding!$K$12*SQRT(ReviewPeriod_R+LeadTime_L)*(ServiceZ*UnitPrice_p*(1-Margin_m)*HoldRate_h+(365/ReviewPeriod_R)*(NORMDIST(ServiceZ,0,1,FALSE)-ServiceZ*(1-NORMSDIST(ServiceZ)))*Margin_m*UnitPrice_p) -> 977.11743 | F8: =ABS(E8-D8) -> 0 | G8: =RANK(F8,$F$4:$F$8) -> 5

Sheet TwoWay
A1: Finding (EUR per store-year): lead time L (rows) x margin m (columns)
A3: L \ m | B3: 0.15 | C3: 0.225 | D3: 0.3 | E3: 0.4 | F3: 0.5
A4: 2 | B4: =Finding!$K$12*SQRT(ReviewPeriod_R+$A4)*(ServiceZ*UnitPrice_p*(1-B$3)*HoldRate_h+(365/ReviewPeriod_R)*(NORMDIST(ServiceZ,0,1,FALSE)-ServiceZ*(1-NORMSDIST(ServiceZ)))*B$3*UnitPrice_p) -> 706.15816 | C4: =Finding!$K$12*SQRT(ReviewPeriod_R+$A4)*(ServiceZ*UnitPrice_p*(1-C$3)*HoldRate_h+(365/ReviewPeriod_R)*(NORMDIST(ServiceZ,0,1,FALSE)-ServiceZ*(1-NORMSDIST(ServiceZ)))*C$3*UnitPrice_p) -> 776.18334 | D4: =Finding!$K$12*SQRT(ReviewPeriod_R+$A4)*(ServiceZ*UnitPrice_p*(1-D$3)*HoldRate_h+(365/ReviewPeriod_R)*(NORMDIST(ServiceZ,0,1,FALSE)-ServiceZ*(1-NORMSDIST(ServiceZ)))*D$3*UnitPrice_p) -> 846.20851 | E4: =Finding!$K$12*SQRT(ReviewPeriod_R+$A4)*(ServiceZ*UnitPrice_p*(1-E$3)*HoldRate_h+(365/ReviewPeriod_R)*(NORMDIST(ServiceZ,0,1,FALSE)-ServiceZ*(1-NORMSDIST(ServiceZ)))*E$3*UnitPrice_p) -> 939.57542 | F4: =Finding!$K$12*SQRT(ReviewPeriod_R+$A4)*(ServiceZ*UnitPrice_p*(1-F$3)*HoldRate_h+(365/ReviewPeriod_R)*(NORMDIST(ServiceZ,0,1,FALSE)-ServiceZ*(1-NORMSDIST(ServiceZ)))*F$3*UnitPrice_p) -> 1032.9423
A5: 3 | B5: =Finding!$K$12*SQRT(ReviewPeriod_R+$A5)*(ServiceZ*UnitPrice_p*(1-B$3)*HoldRate_h+(365/ReviewPeriod_R)*(NORMDIST(ServiceZ,0,1,FALSE)-ServiceZ*(1-NORMSDIST(ServiceZ)))*B$3*UnitPrice_p) -> 744.35605 | C5: =Finding!$K$12*SQRT(ReviewPeriod_R+$A5)*(ServiceZ*UnitPrice_p*(1-C$3)*HoldRate_h+(365/ReviewPeriod_R)*(NORMDIST(ServiceZ,0,1,FALSE)-ServiceZ*(1-NORMSDIST(ServiceZ)))*C$3*UnitPrice_p) -> 818.16907 | D5: =Finding!$K$12*SQRT(ReviewPeriod_R+$A5)*(ServiceZ*UnitPrice_p*(1-D$3)*HoldRate_h+(365/ReviewPeriod_R)*(NORMDIST(ServiceZ,0,1,FALSE)-ServiceZ*(1-NORMSDIST(ServiceZ)))*D$3*UnitPrice_p) -> 891.98209 | E5: =Finding!$K$12*SQRT(ReviewPeriod_R+$A5)*(ServiceZ*UnitPrice_p*(1-E$3)*HoldRate_h+(365/ReviewPeriod_R)*(NORMDIST(ServiceZ,0,1,FALSE)-ServiceZ*(1-NORMSDIST(ServiceZ)))*E$3*UnitPrice_p) -> 990.39945 | F5: =Finding!$K$12*SQRT(ReviewPeriod_R+$A5)*(ServiceZ*UnitPrice_p*(1-F$3)*HoldRate_h+(365/ReviewPeriod_R)*(NORMDIST(ServiceZ,0,1,FALSE)-ServiceZ*(1-NORMSDIST(ServiceZ)))*F$3*UnitPrice_p) -> 1088.8168
A6: 5 | B6: =Finding!$K$12*SQRT(ReviewPeriod_R+$A6)*(ServiceZ*UnitPrice_p*(1-B$3)*HoldRate_h+(365/ReviewPeriod_R)*(NORMDIST(ServiceZ,0,1,FALSE)-ServiceZ*(1-NORMSDIST(ServiceZ)))*B$3*UnitPrice_p) -> 815.4012 | C6: =Finding!$K$12*SQRT(ReviewPeriod_R+$A6)*(ServiceZ*UnitPrice_p*(1-C$3)*HoldRate_h+(365/ReviewPeriod_R)*(NORMDIST(ServiceZ,0,1,FALSE)-ServiceZ*(1-NORMSDIST(ServiceZ)))*C$3*UnitPrice_p) -> 896.25931 | D6: =Finding!$K$12*SQRT(ReviewPeriod_R+$A6)*(ServiceZ*UnitPrice_p*(1-D$3)*HoldRate_h+(365/ReviewPeriod_R)*(NORMDIST(ServiceZ,0,1,FALSE)-ServiceZ*(1-NORMSDIST(ServiceZ)))*D$3*UnitPrice_p) -> 977.11743 | E6: =Finding!$K$12*SQRT(ReviewPeriod_R+$A6)*(ServiceZ*UnitPrice_p*(1-E$3)*HoldRate_h+(365/ReviewPeriod_R)*(NORMDIST(ServiceZ,0,1,FALSE)-ServiceZ*(1-NORMSDIST(ServiceZ)))*E$3*UnitPrice_p) -> 1084.9282 | F6: =Finding!$K$12*SQRT(ReviewPeriod_R+$A6)*(ServiceZ*UnitPrice_p*(1-F$3)*HoldRate_h+(365/ReviewPeriod_R)*(NORMDIST(ServiceZ,0,1,FALSE)-ServiceZ*(1-NORMSDIST(ServiceZ)))*F$3*UnitPrice_p) -> 1192.7391
A7: 7 | B7: =Finding!$K$12*SQRT(ReviewPeriod_R+$A7)*(ServiceZ*UnitPrice_p*(1-B$3)*HoldRate_h+(365/ReviewPeriod_R)*(NORMDIST(ServiceZ,0,1,FALSE)-ServiceZ*(1-NORMSDIST(ServiceZ)))*B$3*UnitPrice_p) -> 880.73396 | C7: =Finding!$K$12*SQRT(ReviewPeriod_R+$A7)*(ServiceZ*UnitPrice_p*(1-C$3)*HoldRate_h+(365/ReviewPeriod_R)*(NORMDIST(ServiceZ,0,1,FALSE)-ServiceZ*(1-NORMSDIST(ServiceZ)))*C$3*UnitPrice_p) -> 968.0707 | D7: =Finding!$K$12*SQRT(ReviewPeriod_R+$A7)*(ServiceZ*UnitPrice_p*(1-D$3)*HoldRate_h+(365/ReviewPeriod_R)*(NORMDIST(ServiceZ,0,1,FALSE)-ServiceZ*(1-NORMSDIST(ServiceZ)))*D$3*UnitPrice_p) -> 1055.4074 | E7: =Finding!$K$12*SQRT(ReviewPeriod_R+$A7)*(ServiceZ*UnitPrice_p*(1-E$3)*HoldRate_h+(365/ReviewPeriod_R)*(NORMDIST(ServiceZ,0,1,FALSE)-ServiceZ*(1-NORMSDIST(ServiceZ)))*E$3*UnitPrice_p) -> 1171.8564 | F7: =Finding!$K$12*SQRT(ReviewPeriod_R+$A7)*(ServiceZ*UnitPrice_p*(1-F$3)*HoldRate_h+(365/ReviewPeriod_R)*(NORMDIST(ServiceZ,0,1,FALSE)-ServiceZ*(1-NORMSDIST(ServiceZ)))*F$3*UnitPrice_p) -> 1288.3054
A8: 10 | B8: =Finding!$K$12*SQRT(ReviewPeriod_R+$A8)*(ServiceZ*UnitPrice_p*(1-B$3)*HoldRate_h+(365/ReviewPeriod_R)*(NORMDIST(ServiceZ,0,1,FALSE)-ServiceZ*(1-NORMSDIST(ServiceZ)))*B$3*UnitPrice_p) -> 970.52155 | C8: =Finding!$K$12*SQRT(ReviewPeriod_R+$A8)*(ServiceZ*UnitPrice_p*(1-C$3)*HoldRate_h+(365/ReviewPeriod_R)*(NORMDIST(ServiceZ,0,1,FALSE)-ServiceZ*(1-NORMSDIST(ServiceZ)))*C$3*UnitPrice_p) -> 1066.762 | D8: =Finding!$K$12*SQRT(ReviewPeriod_R+$A8)*(ServiceZ*UnitPrice_p*(1-D$3)*HoldRate_h+(365/ReviewPeriod_R)*(NORMDIST(ServiceZ,0,1,FALSE)-ServiceZ*(1-NORMSDIST(ServiceZ)))*D$3*UnitPrice_p) -> 1163.0024 | E8: =Finding!$K$12*SQRT(ReviewPeriod_R+$A8)*(ServiceZ*UnitPrice_p*(1-E$3)*HoldRate_h+(365/ReviewPeriod_R)*(NORMDIST(ServiceZ,0,1,FALSE)-ServiceZ*(1-NORMSDIST(ServiceZ)))*E$3*UnitPrice_p) -> 1291.3229 | F8: =Finding!$K$12*SQRT(ReviewPeriod_R+$A8)*(ServiceZ*UnitPrice_p*(1-F$3)*HoldRate_h+(365/ReviewPeriod_R)*(NORMDIST(ServiceZ,0,1,FALSE)-ServiceZ*(1-NORMSDIST(ServiceZ)))*F$3*UnitPrice_p) -> 1419.6434

Sheet Checks
A1: Sanity limit cases (live)
A3: Check | B3: Value | C3: Pass
A4: Zero error gives zero extra cost | B4: =0*K_factor -> 0 | C4: =ABS(B4)<0.000000000001 -> TRUE
A5: Equal promo and ordinary error gives zero finding | B5: =(100-100)*K_factor -> 0 | C5: =ABS(B5)<0.000000000001 -> TRUE
A6: Extra cost is increasing in sigma (2s minus s) | B6: =200*K_factor-100*K_factor -> 212.92965 | C6: =B6>0 -> TRUE
A7: Formula chain equals mean of per-store findings | B7: =Finding!K27-Finding!K4 -> 0 | C7: =ABS(B7)<0.000001*MAX(1,ABS(Finding!K4)) -> TRUE
A8: No error cells in the finding column | B8: =SUMPRODUCT(--ISERROR(Finding!E4:E1118)) -> 0 | C8: =B8=0 -> TRUE
A10: Overall | B10: =IF(AND(C4:C8),"ALL CHECKS PASS","CHECK FAILED") -> ALL CHECKS PASS
